{
  "navPills": [
    { "tabName": "tabTopClothes", "showName": "Áo", "type": "topclothes" },
    { "tabName": "tabBotClothes", "showName": "Quần", "type": "botclothes" },
    { "tabName": "tabShoes", "showName": "Giày dép", "type": "shoes" },
    { "tabName": "tabHandBags", "showName": "Túi xách", "type": "handbags" },
    { "tabName": "tabNecklaces", "showName": "Dây chuyền", "type": "necklaces" },
    { "tabName": "tabHairStyle", "showName": "Kiểu tóc", "type": "hairstyle" },
    { "tabName": "tabBackground", "showName": "Nền", "type": "background" }
  ],
  "tabPanes": [
    {
      "id": "topcloth_1",
      "type": "topclothes",
      "name": "Top Cloth 1",
      "desc": "Lorem ipsum dolor, sit amet consectetur adipisicing elit. Aliquid, nulla.",
      "imgSrc_jpg": "./images/clothes/topcloth1_show.jpg",
      "imgSrc_png": "./images/clothes/topclothOne.png"
    },
    {
      "id": "topcloth_2",
      "type": "topclothes",
      "name": "Top Cloth 2",
      "desc": "Lorem ipsum dolor, sit amet consectetur adipisicing elit. Aliquid, nulla.",
      "imgSrc_jpg": "./images/clothes/topcloth2_show.jpg",
      "imgSrc_png": "./images/clothes/topclothTwo.png"
    },
    {
      "id": "topcloth_3",
      "type": "topclothes",
      "name": "Top Cloth 3",
      "desc": "Lorem ipsum dolor, sit amet consectetur adipisicing elit. Aliquid, nulla.",
      "imgSrc_jpg": "./images/clothes/topcloth3_show.jpg",
      "imgSrc_png": "./images/clothes/topclothThree.png"
    },
    {
      "id": "topcloth_4",
      "type": "topclothes",
      "name": "Top Cloth 4",
      "desc": "Lorem ipsum dolor, sit amet consectetur adipisicing elit. Aliquid, nulla.",
      "imgSrc_jpg": "./images/clothes/topcloth4_show.jpg",
      "imgSrc_png": "./images/clothes/topclothFour.png"
    },
    {
      "id": "topcloth_5",
      "type": "topclothes",
      "name": "Top Cloth 5",
      "desc": "Lorem ipsum dolor, sit amet consectetur adipisicing elit. Aliquid, nulla.",
      "imgSrc_jpg": "./images/clothes/topcloth5_show.jpg",
      "imgSrc_png": "./images/clothes/topclothFive.png"
    },
    {
      "id": "topcloth_6",
      "type": "topclothes",
      "name": "Top Cloth 6",
      "desc": "Lorem ipsum dolor, sit amet consectetur adipisicing elit. Aliquid, nulla.",
      "imgSrc_jpg": "./images/clothes/topcloth6_show.jpg",
      "imgSrc_png": "./images/clothes/topclothSix.png"
    },
    {
      "id": "botcloth_1",
      "type": "botclothes",
      "name": "Bot Cloth 1",
      "desc": "Lorem ipsum dolor, sit amet consectetur adipisicing elit. Aliquid, nulla.",
      "imgSrc_jpg": "./images/clothes/botcloth1_show.jpg",
      "imgSrc_png": "./images/clothes/botclothOne.png"
    },
    {
      "id": "botcloth_2",
      "type": "botclothes",
      "name": "Bot Cloth 2",
      "desc": "Lorem ipsum dolor, sit amet consectetur adipisicing elit. Aliquid, nulla.",
      "imgSrc_jpg": "./images/clothes/botcloth2_show.jpg",
      "imgSrc_png": "./images/clothes/botclothTwo.png"
    },
    {
      "id": "botcloth_3",
      "type": "botclothes",
      "name": "Bot Cloth 3",
      "desc": "Lorem ipsum dolor, sit amet consectetur adipisicing elit. Aliquid, nulla.",
      "imgSrc_jpg": "./images/clothes/botcloth3_show.jpg",
      "imgSrc_png": "./images/clothes/botclothThree.png"
    },
    {
      "id": "botcloth_4",
      "type": "botclothes",
      "name": "Bot Cloth 4",
      "desc": "Lorem ipsum dolor, sit amet consectetur adipisicing elit. Aliquid, nulla.",
      "imgSrc_jpg": "./images/clothes/botcloth4_show.jpg",
      "imgSrc_png": "./images/clothes/botclothFour.png"
    },
    {
      "id": "botcloth_5",
      "type": "botclothes",
      "name": "Bot Cloth 5",
      "desc": "Lorem ipsum dolor, sit amet consectetur adipisicing elit. Aliquid, nulla.",
      "imgSrc_jpg": "./images/clothes/botcloth5_show.jpg",
      "imgSrc_png": "./images/clothes/botclothFive.png"
    },
    {
      "id": "shoes_1",
      "type": "shoes",
      "name": "Shoes 1",
      "desc": "Lorem ipsum dolor, sit amet consectetur adipisicing elit. Aliquid, nulla.",
      "imgSrc_jpg": "./images/shoes/shoes1_show.jpg",
      "imgSrc_png": "./images/shoes/shoesOne.png"
    },
    {
      "id": "shoes_2",
      "type": "shoes",
      "name": "Shoes 2",
      "desc": "Lorem ipsum dolor, sit amet consectetur adipisicing elit. Aliquid, nulla.",
      "imgSrc_jpg": "./images/shoes/shoes2_show.jpg",
      "imgSrc_png": "./images/shoes/shoesTwo.png"
    },
    {
      "id": "shoes_3",
      "type": "shoes",
      "name": "Shoes 3",
      "desc": "Lorem ipsum dolor, sit amet consectetur adipisicing elit. Aliquid, nulla.",
      "imgSrc_jpg": "./images/shoes/shoes3_show.jpg",
      "imgSrc_png": "./images/shoes/shoesThree.png"
    },
    {
      "id": "shoes_4",
      "type": "shoes",
      "name": "Shoes 4",
      "desc": "Lorem ipsum dolor, sit amet consectetur adipisicing elit. Aliquid, nulla.",
      "imgSrc_jpg": "./images/shoes/shoes4_show.jpg",
      "imgSrc_png": "./images/shoes/shoesFour.png"
    },
    {
      "id": "shoes_5",
      "type": "shoes",
      "name": "Shoes 5",
      "desc": "Lorem ipsum dolor, sit amet consectetur adipisicing elit. Aliquid, nulla.",
      "imgSrc_jpg": "./images/shoes/shoes5_show.jpg",
      "imgSrc_png": "./images/shoes/shoesFive.png"
    },
    {
      "id": "handbag_1",
      "type": "handbags",
      "name": "Handbag 1",
      "desc": "Lorem ipsum dolor, sit amet consectetur adipisicing elit. Aliquid, nulla.",
      "imgSrc_jpg": "./images/handbags/handbag1_show.jpg",
      "imgSrc_png": "./images/handbags/handbagOne.png"
    },
    {
      "id": "handbag_2",
      "type": "handbags",
      "name": "Handbag 2",
      "desc": "Lorem ipsum dolor, sit amet consectetur adipisicing elit. Aliquid, nulla.",
      "imgSrc_jpg": "./images/handbags/handbag2_show.jpg",
      "imgSrc_png": "./images/handbags/handbagTwo.png"
    },
    {
      "id": "handbag_3",
      "type": "handbags",
      "name": "Handbag 3",
      "desc": "Lorem ipsum dolor, sit amet consectetur adipisicing elit. Aliquid, nulla.",
      "imgSrc_jpg": "./images/handbags/handbag3_show.jpg",
      "imgSrc_png": "./images/handbags/handbagThree.png"
    },
    {
      "id": "necklace_1",
      "type": "necklaces",
      "name": "Necklace 1",
      "desc": "Lorem ipsum dolor, sit amet consectetur adipisicing elit. Aliquid, nulla.",
      "imgSrc_jpg": "./images/necklaces/necklace1_show.jpg",
      "imgSrc_png": "./images/necklaces/necklaceOne.png"
    },
    {
      "id": "necklace_2",
      "type": "necklaces",
      "name": "Necklace 2",
      "desc": "Lorem ipsum dolor, sit amet consectetur adipisicing elit. Aliquid, nulla.",
      "imgSrc_jpg": "./images/necklaces/necklace2_show.jpg",
      "imgSrc_png": "./images/necklaces/necklaceTwo.png"
    },
    {
      "id": "necklace_3",
      "type": "necklaces",
      "name": "Necklace 3",
      "desc": "Lorem ipsum dolor, sit amet consectetur adipisicing elit. Aliquid, nulla.",
      "imgSrc_jpg": "./images/necklaces/necklace3_show.jpg",
      "imgSrc_png": "./images/necklaces/necklaceThree.png"
    },
    {
      "id": "hairstyle_1",
      "type": "hairstyle",
      "name": "Hairstyle 1",
      "desc": "Lorem ipsum dolor, sit amet consectetur adipisicing elit. Aliquid, nulla.",
      "imgSrc_jpg": "./images/hairstyle/hairstyle1_show.jpg",
      "imgSrc_png": "./images/hairstyle/hairstyleOne.png"
    },
    {
      "id": "hairstyle_2",
      "type": "hairstyle",
      "name": "Hairstyle 2",
      "desc": "Lorem ipsum dolor, sit amet consectetur adipisicing elit. Aliquid, nulla.",
      "imgSrc_jpg": "./images/hairstyle/hairstyle2_show.jpg",
      "imgSrc_png": "./images/hairstyle/hairstyleTwo.png"
    },
    {
      "id": "hairstyle_3",
      "type": "hairstyle",
      "name": "Hairstyle 3",
      "desc": "Lorem ipsum dolor, sit amet consectetur adipisicing elit. Aliquid, nulla.",
      "imgSrc_jpg": "./images/hairstyle/hairstyle3_show.jpg",
      "imgSrc_png": "./images/hairstyle/hairstyleThree.png"
    },
    {
      "id": "background_1",
      "type": "background",
      "name": "Background 1",
      "desc": "Lorem ipsum dolor, sit amet consectetur adipisicing elit. Aliquid, nulla.",
      "imgSrc_jpg": "./images/background/background1_show.jpg",
      "imgSrc_png": "./images/background/backgroundOne.jpg"
    },
    {
      "id": "background_2",
      "type": "background",
      "name": "Background 2",
      "desc": "Lorem ipsum dolor, sit amet consectetur adipisicing elit. Aliquid, nulla.",
      "imgSrc_jpg": "./images/background/background2_show.jpg",
      "imgSrc_png": "./images/background/backgroundTwo.jpg"
    },
    {
      "id": "background_3",
      "type": "background",
      "name": "Background 3",
      "desc": "Lorem ipsum dolor, sit amet consectetur adipisicing elit. Aliquid, nulla.",
      "imgSrc_jpg": "./images/background/background3_show.jpg",
      "imgSrc_png": "./images/background/backgroundThree.jpg"
    },
    {
      "id": "background_4",
      "type": "background",
      "name": "Background 4",
      "desc": "Lorem ipsum dolor, sit amet consectetur adipisicing elit. Aliquid, nulla.",
      "imgSrc_jpg": "./images/background/background4_show.jpg",
      "imgSrc_png": "./images/background/backgroundFour.jpg"
    }
  ]
}
